flask_forge_cli-1.1.0.dist-info/licenses/LICENSE
forge/__init__.py
forge/cli.py
forge/commands/db_cmd.py
forge/commands/generate_cmd.py
forge/commands/plugin_cmd.py
forge/commands/run_cmd.py
forge/templates/clean/.env.example
forge/templates/clean/pyproject.toml
forge/templates/clean/src/{{package_name}}/main.py
forge/templates/clean/src/{{package_name}}/infra/db/base.py
forge/templates/clean/src/{{package_name}}/interfaces/http/api.py
forge/templates/clean/src/{{package_name}}/shared/config.py
forge/templates/clean/src/{{package_name}}/shared/di.py
forge/templates/clean/src/{{package_name}}/shared/di_wiring.py
forge/templates/clean/src/{{package_name}}/shared/logging.py
forge/templates/clean/tests/test_health.py
forge/utils/fs.py
flask_forge_cli-1.1.0.dist-info/METADATA
flask_forge_cli-1.1.0.dist-info/WHEEL
flask_forge_cli-1.1.0.dist-info/entry_points.txt
flask_forge_cli-1.1.0.dist-info/top_level.txt
flask_forge_cli-1.1.0.dist-info/RECORD
