Metadata-Version: 2.4
Name: flask-forge-cli
Version: 1.1.0
Summary: Clean Architecture scaffolding for Flask (OOP-first)
Author: Kevin Martinez
Requires-Python: >=3.11
License-File: LICENSE
Requires-Dist: typer>=0.12
Requires-Dist: jinja2>=3.1
Requires-Dist: rich>=13.7
Requires-Dist: flask_smorest>=0.41.0
Provides-Extra: dev
Requires-Dist: black>=24.8.0; extra == "dev"
Requires-Dist: ruff>=0.6.9; extra == "dev"
Requires-Dist: pre-commit>=3.4.0; extra == "dev"
Requires-Dist: pytest>=7.4.0; extra == "dev"
Requires-Dist: rich>=13.7; extra == "dev"
Requires-Dist: requests>=2.31.0; extra == "dev"
Requires-Dist: build>=0.10.0; extra == "dev"
Requires-Dist: twine>=4.0.2; extra == "dev"
Requires-Dist: setuptools>=68; extra == "dev"
Requires-Dist: wheel>=0.40.0; extra == "dev"
Dynamic: license-file
